Photolab/__init__.py
Photolab/basic_op_col.py
Photolab/edge.py
Photolab/freq_filter.py
Photolab/img_restore.py
Photolab/noise.py
Photolab/spatial_bw.py
photolab-0.1.0.dist-info/License.txt
photolab-0.1.0.dist-info/METADATA
photolab-0.1.0.dist-info/WHEEL
photolab-0.1.0.dist-info/top_level.txt
photolab-0.1.0.dist-info/RECORD
